patchai/__init__.py
patchai/cli.py
patchai/diff.py
patchai/editor.py
patchai/jupyter.py
patchai-0.1.5.dist-info/METADATA
patchai-0.1.5.dist-info/WHEEL
patchai-0.1.5.dist-info/entry_points.txt
patchai-0.1.5.dist-info/licenses/LICENSE
patchai-0.1.5.dist-info/RECORD
