Metadata-Version: 2.4
Name: patchai
Version: 0.1.5
Summary: AI-powered structured file editor with diff visualization
Project-URL: Homepage, https://github.com/davidkjeremiah/patchai
Project-URL: Documentation, https://github.com/davidkjeremiah/patchai/blob/main/README.md
Project-URL: Repository, https://github.com/davidkjeremiah/patchai
Project-URL: Issues, https://github.com/davidkjeremiah/patchai/issues
Author-email: David Jeremiah <flasconnect@gmail.com>
License: MIT
License-File: LICENSE
Keywords: ai,config,diff,editor,json,llm,yaml
Classifier: Development Status :: 3 - Alpha
Classifier: Intended Audience :: Developers
Classifier: License :: OSI Approved :: MIT License
Classifier: Programming Language :: Python :: 3
Classifier: Programming Language :: Python :: 3.8
Classifier: Programming Language :: Python :: 3.9
Classifier: Programming Language :: Python :: 3.10
Classifier: Programming Language :: Python :: 3.11
Classifier: Programming Language :: Python :: 3.12
Classifier: Topic :: Software Development :: Libraries :: Python Modules
Classifier: Topic :: Text Editors
Requires-Python: >=3.8
Requires-Dist: pyyaml>=6.0
Requires-Dist: rich>=13.0.0
Provides-Extra: all-providers
Requires-Dist: anthropic; extra == 'all-providers'
Requires-Dist: google-genai; extra == 'all-providers'
Requires-Dist: openai; extra == 'all-providers'
Provides-Extra: anthropic
Requires-Dist: anthropic; extra == 'anthropic'
Provides-Extra: dev
Requires-Dist: black; extra == 'dev'
Requires-Dist: pytest; extra == 'dev'
Requires-Dist: ruff; extra == 'dev'
Provides-Extra: gemini
Requires-Dist: google-genai; extra == 'gemini'
Provides-Extra: jupyter
Requires-Dist: ipython; extra == 'jupyter'
Requires-Dist: ipywidgets; extra == 'jupyter'
Provides-Extra: openai
Requires-Dist: openai; extra == 'openai'
